llm_team/__init__.py
llm_team/playground.py
llm_team/agents/__init__.py
llm_team/agents/agents_with_memory.py
llm_team/agents/basic_agent.py
llm_team/agents/messages.py
llm_team/agents/models.py
llm_team/agents/team_creation.py
llm_team/agents/tests/test_agents_with_memory.py
llm_team/agents/tests/test_basic_agent.py
llm_team/agents/tests/test_messages.py
llm_team/agents/tests/test_team_creator_agent.py
llm_team/agents/tools/__init__.py
llm_team/agents/tools/base_tool.py
llm_team/agents/tools/conversation.py
llm_team/agents/tools/file_tools.py
llm_team/agents/tools/mathematical.py
llm_team/agents/tools/search_tools.py
llm_team/agents/tools/tests/test_tools.py
llm_team/agents/tools/utils/hierachal_retriever.py
llm_team/agents/utils/team_creator_utils.py
llm_team/config/__init__.py
llm_team/config/configuration.py
llm_team/config/project_paths.py
llm_team/config/project_secrets.py
llm_team/conversations/__init__.py
llm_team/conversations/base_conversation.py
llm_team/conversations/cli_conversation.py
llm_team/conversations/messages.py
llm_team/conversations/participants.py
llm_team/data/conversations/Unnamed_messages.json
llm_team/data/introspection/Unnamed/Manager_introspection.json
llm_team/database/__init__.py
llm_team/database/db.py
llm_team/internal/config_loader.py
llm_team/projects/__init__.py
llm_team/projects/project.py
llm_team/resources/__init__.py
llm_team/resources/standard_gitignore.txt
llm_team/teams/__init__.py
llm_team/teams/team.py
llm_team/telemetry/__init__.py
llm_team/telemetry/agent_telemetry.py
llm_team/telemetry/common.py
llm_team/telemetry/conversation_telemetry.py
llm_team/utils/__init__.py
llm_team/utils/database.py
llm_team/utils/exceptions.py
llm_team/utils/module_exports.py
llm_team/utils/serialization.py
llm_team/utils/tests/test_database.py
llm_team/utils/tests/test_module_exports.py
llm_team-0.1.8.dist-info/METADATA
llm_team-0.1.8.dist-info/WHEEL
llm_team-0.1.8.dist-info/RECORD
