Metadata-Version: 2.3
Name: llm-team
Version: 0.1.8
Summary: Add your description here
Requires-Python: >=3.10
Requires-Dist: anthropic>=0.38.0
Requires-Dist: coverage>=7.6.4
Requires-Dist: duckduckgo-search>=6.3.5
Requires-Dist: fastapi>=0.115.4
Requires-Dist: peewee>=3.17.7
Requires-Dist: pynput>=1.7.7
Requires-Dist: pytest>=8.3.3
Requires-Dist: python-dotenv>=1.0.1
Requires-Dist: sqlmodel>=0.0.22
Requires-Dist: tavily-python>=0.5.0
Requires-Dist: uvicorn>=0.32.0
